elements/half_adder.sv
module half_adder (
    input logic x,
    input logic y,
    output logic sum,
    output logic carry

);  

assign sum = x^y;
assign carry = x&y;
    
endmodule;

elements/full_adder.sv
module full_adder (
    input logic x,
    input logic y,
    input logic c_in,
    output logic sum,
    output logic carry

);

logic sum_a, c_a, sum_b, c_b;
half_adder ha1(x, y, sum_a, c_a);
half_adder ha2(sum_a, c_in, sum_b, c_b);

assign sum = sum_b;
assign carry = c_a | c_b;

    
endmodule;

tb/full_adder_tb.sv
`timescale 1ns / 1ns

module full_adder_tb;

  logic x, y, cin, sum, cout;

  full_adder full_adder_inst (
      x,
      y,
      cin,
      sum,
      cout
  );

  initial begin
    x   = 0;
    y   = 0;
    cin = 0;
    #10;
    $display("x = %b, y = %b, cin = %b, sum = %b, cout = %b", x, y, cin, sum, cout);
    x   = 0;
    y   = 0;
    cin = 1;
    #10;
    $display("x = %b, y = %b, cin = %b, sum = %b, cout = %b", x, y, cin, sum, cout);
    x   = 0;
    y   = 1;
    cin = 0;
    #10;
    $display("x = %b, y = %b, cin = %b, sum = %b, cout = %b", x, y, cin, sum, cout);
    x   = 0;
    y   = 1;
    cin = 1;
    #10;
    $display("x = %b, y = %b, cin = %b, sum = %b, cout = %b", x, y, cin, sum, cout);
    x   = 1;
    y   = 0;
    cin = 0;
    #10;
    $display("x = %b, y = %b, cin = %b, sum = %b, cout = %b", x, y, cin, sum, cout);
    x   = 1;
    y   = 0;
    cin = 1;
    #10;
    $display("x = %b, y = %b, cin = %b, sum = %b, cout = %b", x, y, cin, sum, cout);
    x   = 1;
    y   = 1;
    cin = 0;
    #10;
    $display("x = %b, y = %b, cin = %b, sum = %b, cout = %b", x, y, cin, sum, cout);
    x   = 1;
    y   = 1;
    cin = 1;
    #10;
    $display("x = %b, y = %b, cin = %b, sum = %b, cout = %b", x, y, cin, sum, cout);
    #10;
    $finish;
  end
endmodule

full_adder.vcd
$version Generated by VerilatedVcd $end
$timescale 1ns $end
 $scope module TOP $end
  $scope module full_adder_tb $end
   $var wire 1 # x $end
   $var wire 1 $ y $end
   $var wire 1 % cin $end
   $var wire 1 & sum $end
   $var wire 1 ' cout $end
   $scope module full_adder_inst $end
    $var wire 1 # x $end
    $var wire 1 $ y $end
    $var wire 1 % c_in $end
    $var wire 1 & sum $end
    $var wire 1 ' carry $end
    $var wire 1 ( sum_a $end
    $var wire 1 ) c_a $end
    $var wire 1 & sum_b $end
    $var wire 1 * c_b $end
    $scope module ha1 $end
     $var wire 1 # x $end
     $var wire 1 $ y $end
     $var wire 1 ( sum $end
     $var wire 1 ) carry $end
    $upscope $end
    $scope module ha2 $end
     $var wire 1 ( x $end
     $var wire 1 % y $end
     $var wire 1 & sum $end
     $var wire 1 * carry $end
    $upscope $end
   $upscope $end
  $upscope $end
 $upscope $end
$enddefinitions $end


#0
0#
0$
0%
0&
0'
0(
0)
0*
#1
#2
#3
#4
#5
#6
#7
#8
#9
#10
1%
1&
#11
#12
#13
#14
#15
#16
#17
#18
#19
#20
1$
0%
1(
#21
#22
#23
#24
#25
#26
#27
#28
#29
#30
1%
0&
1'
1*
#31
#32
#33
#34
#35
#36
#37
#38
#39
#40
1#
0$
0%
1&
0'
0*
#41
#42
#43
#44
#45
#46
#47
#48
#49
#50
1%
0&
1'
1*
#51
#52
#53
#54
#55
#56
#57
#58
#59
#60
1$
0%
0(
1)
0*
#61
#62
#63
#64
#65
#66
#67
#68
#69
#70
1%
1&
